plagy/__init__.py
plagy/plagy.py
plagy_mnk-0.1.1.dist-info/LICENSE
plagy_mnk-0.1.1.dist-info/METADATA
plagy_mnk-0.1.1.dist-info/WHEEL
plagy_mnk-0.1.1.dist-info/top_level.txt
plagy_mnk-0.1.1.dist-info/RECORD
