Metadata-Version: 2.1
Name: plagy-mnk
Version: 0.1.1
Summary: A Simple Plagiarism Checker
Home-page: https://github.com/mnk-q/plagy
Author: Manish Pandey
Author-email: mnkp.qc@gmail.com
License: UNKNOWN
Project-URL: Bug Tracker, https://github.com/mnk-q/plagy/issues
Platform: UNKNOWN
Classifier: Programming Language :: Python :: 3
Classifier: License :: OSI Approved :: MIT License
Classifier: Operating System :: OS Independent
Requires-Python: >=3.6
License-File: LICENSE
Requires-Dist: scikit-learn
